jcramda/__init__.py
jcramda/__init__.pyi
jcramda/base/__init__.py
jcramda/base/__init__.pyi
jcramda/base/comparison.py
jcramda/base/comparison.pyi
jcramda/base/datetimes.py
jcramda/base/datetimes.pyi
jcramda/base/enumtools.py
jcramda/base/enumtools.pyi
jcramda/base/functions.py
jcramda/base/functions.pyi
jcramda/base/mapping.py
jcramda/base/mapping.pyi
jcramda/base/sequence.py
jcramda/base/sequence.pyi
jcramda/base/text.py
jcramda/base/text.pyi
jcramda/core/__init__.py
jcramda/core/_curry.py
jcramda/core/compose.py
jcramda/core/itertools.py
jcramda/core/operator.py
jcramda/core.pyi
jcramda/factor/__init__.py
jcramda-1.0.6.dist-info/LICENSE
jcramda-1.0.6.dist-info/WHEEL
jcramda-1.0.6.dist-info/METADATA
jcramda-1.0.6.dist-info/RECORD
