Metadata-Version: 2.1
Name: jcramda
Version: 1.0.6
Summary: functional programming tools in python
License: MIT
Author: Jochen.He
Author-email: thjl@hotmail.com
Requires-Python: >=3.8,<4.0
Classifier: License :: OSI Approved :: MIT License
Classifier: Programming Language :: Python :: 3
Classifier: Programming Language :: Python :: 3.8
Classifier: Programming Language :: Python :: 3.9
Requires-Dist: more-itertools (>=8.10.0,<9.0.0)
Requires-Dist: python-dateutil (>=2.8.2,<3.0.0)
Requires-Dist: pytz (>=2021.1,<2022.0)
